MPYdata/MPYdata.py
MPYdata/__init__.py
MPYdata/import MPYdata1.py
MPYdata-5.0.0.dist-info/LICENSE.txt
MPYdata-5.0.0.dist-info/METADATA
MPYdata-5.0.0.dist-info/WHEEL
MPYdata-5.0.0.dist-info/top_level.txt
MPYdata-5.0.0.dist-info/RECORD
